cell_mosaics/__init__.py
cell_mosaics/coverage.py
cell_mosaics/plotting.py
cell_mosaics/toy_data.py
cell_mosaics/toy_data_demo.ipynb
cell_mosaics-0.1.1.dist-info/METADATA
cell_mosaics-0.1.1.dist-info/WHEEL
cell_mosaics-0.1.1.dist-info/licenses/LICENSE
cell_mosaics-0.1.1.dist-info/RECORD
