Metadata-Version: 2.4
Name: cell-mosaics
Version: 0.1.1
Summary: Tools for computing and visualizing coverage density maps for cell outlines
Project-URL: Homepage, https://github.com/berenslab/cell_mosaics
Project-URL: Issues, https://github.com/berenslab/cell_mosaics/issues
Author: berenslab
License: MIT
License-File: LICENSE
Requires-Python: >=3.10
Requires-Dist: matplotlib>=3.10.6
Requires-Dist: scikit-image>=0.25.2
Requires-Dist: scipy>=1.16.1
Provides-Extra: dev
Requires-Dist: jupyter>=1.1.1; extra == 'dev'
Requires-Dist: pytest>=8.2; extra == 'dev'
Requires-Dist: scipy-stubs==1.16.1.1; extra == 'dev'
